yolov10/__init__.py
yolov10/utils.py
yolov10/yolov10.py
yolov10_onnx-0.3.0.dist-info/LICENSE
yolov10_onnx-0.3.0.dist-info/METADATA
yolov10_onnx-0.3.0.dist-info/WHEEL
yolov10_onnx-0.3.0.dist-info/top_level.txt
yolov10_onnx-0.3.0.dist-info/RECORD
