Metadata-Version: 2.1
Name: yolov10-onnx
Version: 0.3.0
Summary: Run YOLOv10 model with ONNX Runtime
Author: Ibai Gorordo
License: MIT
Project-URL: Homepage, https://github.com/ibaiGorordo/ONNX-YOLOv10-Object-Detection
License-File: LICENSE
Requires-Dist: opencv-python
Requires-Dist: onnxruntime-gpu==1.18.0; sys_platform != "darwin"
Requires-Dist: onnxruntime==1.18.0; sys_platform == "darwin" and platform_machine != "arm64"
Requires-Dist: onnxruntime-silicon==1.16.3; sys_platform == "darwin" and platform_machine == "arm64"
